msadaptivecards/__init__.py
msadaptivecards/actions.py
msadaptivecards/base.py
msadaptivecards/cards.py
msadaptivecards/containers.py
msadaptivecards/elements.py
msadaptivecards/py.typed
ms_adaptive_cards-0.1.1.dist-info/LICENSE
ms_adaptive_cards-0.1.1.dist-info/WHEEL
ms_adaptive_cards-0.1.1.dist-info/METADATA
ms_adaptive_cards-0.1.1.dist-info/RECORD
