Metadata-Version: 2.1
Name: ms-adaptive-cards
Version: 0.1.1
Summary: Python implementation of Microsoft Adaptive Cards
Author: Idar Bergli
Author-email: idarb@pm.me
Requires-Python: >=3.8,<4.0
Classifier: Programming Language :: Python :: 3
Classifier: Programming Language :: Python :: 3.8
Classifier: Programming Language :: Python :: 3.9
Classifier: Programming Language :: Python :: 3.10
Requires-Dist: pydantic (>=1.9.1,<2.0.0)
Requires-Dist: pyhumps (>=3.7.2,<4.0.0)
